facial_keypoints_detecter/__init__.py
facial_keypoints_detecter/auxil.py
facial_keypoints_detecter/data.py
facial_keypoints_detecter/model.py
facial_keypoints_detecter/plots.py
facial_keypoints_detecter/preprocessing.py
facial_keypoints_detecter/__auxil_subpkg__/__init__.py
facial_keypoints_detecter/__auxil_subpkg__/_auxil_submod.py
facial_keypoints_detecter/__auxil_subpkg__/images/_project_readme.png
facial_keypoints_detecter/__auxil_subpkg__/images/face_filter_ex.png
facial_keypoints_detecter/__auxil_subpkg__/images/feature_map_ex.png
facial_keypoints_detecter/__auxil_subpkg__/images/haar_cascade_ex.png
facial_keypoints_detecter/__auxil_subpkg__/images/key_pts_example.png
facial_keypoints_detecter/__auxil_subpkg__/images/landmarks_numbered.jpg
facial_keypoints_detecter/__auxil_subpkg__/images/michelle_detected.png
facial_keypoints_detecter/__auxil_subpkg__/images/mona_lisa.jpg
facial_keypoints_detecter/__auxil_subpkg__/images/moustache.png
facial_keypoints_detecter/__auxil_subpkg__/images/obamas.jpg
facial_keypoints_detecter/__auxil_subpkg__/images/straw_hat.png
facial_keypoints_detecter/__auxil_subpkg__/images/sunglasses.png
facial_keypoints_detecter/__auxil_subpkg__/images/the_beatles.jpg
facial_keypoints_detecter/__constants_subpkg__/__init__.py
facial_keypoints_detecter/__constants_subpkg__/_constants_submod.py
facial_keypoints_detecter/__constants_subpkg__/detector_architectures/haarcascade_eye.xml
facial_keypoints_detecter/__constants_subpkg__/detector_architectures/haarcascade_frontalface_default.xml
facial_keypoints_detecter/__constants_subpkg__/detector_architectures/haarcascade_mcs_nose.xml
facial_keypoints_detecter/__constants_subpkg__/detector_architectures/haarcascade_smile.xml
facial_keypoints_detecter/__constants_subpkg__/filters/_project_readme.png
facial_keypoints_detecter/__constants_subpkg__/filters/face_filter_ex.png
facial_keypoints_detecter/__constants_subpkg__/filters/feature_map_ex.png
facial_keypoints_detecter-1.0.0.dist-info/METADATA
facial_keypoints_detecter-1.0.0.dist-info/WHEEL
facial_keypoints_detecter-1.0.0.dist-info/top_level.txt
facial_keypoints_detecter-1.0.0.dist-info/RECORD
