Metadata-Version: 2.1
Name: facial-keypoints-detecter
Version: 1.0.0
Summary: A CNN based facial keypoints detector.
Home-page: https://github.com/ShashankKumbhare/facial-keypoints-detecter
Author: Shashank Kumbhare
Author-email: shashankkumbhare8@gmail.com
License: MIT
Keywords: facial-keypoints-detecter,facial landmarks,facial filters,PyTorch,torchvision,OpenCV-Python,python,ML,machine learning,AI,artificial intelligence
Platform: UNKNOWN
Classifier: License :: OSI Approved :: MIT License
Classifier: Natural Language :: English
Classifier: Operating System :: OS Independent
Classifier: Programming Language :: Python :: 3
Requires-Dist: numpy
Requires-Dist: pandas
Requires-Dist: matplotlib
Requires-Dist: opencv-python
